__init__.py
pystools/AliyunOss.py
pystools/Amap.py
pystools/Baidudisk.py
pystools/BizResponse.py
pystools/BizResponseCode.py
pystools/FastapiAuthToken.py
pystools/Feishu.py
pystools/FeishuWebhook.py
pystools/Jwt.py
pystools/LexinSms.py
pystools/Logger.py
pystools/MD5util.py
pystools/MediaUtils.py
pystools/MyOpenai.py
pystools/PLogger.py
pystools/RabbitmqServer.py
pystools/RedisUtil.py
pystools/SEOLinksubmit.py
pystools/SEncoder.py
pystools/SeleniumWebDriver.py
pystools/Simage.py
pystools/SplWebhook.py
pystools/TencentCos.py
pystools/Xiumi.py
pystools/__init__.py
pystools/example.py
pystools/baidu_disk/__init__.py
pystools/baidu_disk/api_client.py
pystools/baidu_disk/configuration.py
pystools/baidu_disk/exceptions.py
pystools/baidu_disk/model_utils.py
pystools/baidu_disk/rest.py
pystools/baidu_disk/api/__init__.py
pystools/baidu_disk/api/auth_api.py
pystools/baidu_disk/api/fileinfo_api.py
pystools/baidu_disk/api/filemanager_api.py
pystools/baidu_disk/api/fileupload_api.py
pystools/baidu_disk/api/multimediafile_api.py
pystools/baidu_disk/api/userinfo_api.py
pystools/baidu_disk/model/__init__.py
pystools/baidu_disk/model/oauth_token_authorization_code_response.py
pystools/baidu_disk/model/oauth_token_device_code_response.py
pystools/baidu_disk/model/oauth_token_device_token_response.py
pystools/baidu_disk/model/oauth_token_refresh_token_response.py
pystools/baidu_disk/model/quotaresponse.py
pystools/baidu_disk/model/uinforesponse.py
pystools/baidu_disk/utils/__init__.py
pystools/baidu_disk/utils/auth.py
pystools/baidu_disk/utils/fileinfo.py
pystools/baidu_disk/utils/filemanager.py
pystools/baidu_disk/utils/multimedia_file.py
pystools/baidu_disk/utils/upload.py
pystools/baidu_disk/utils/userinfo.py
pystools-0.0.92.dist-info/LICENSE
pystools-0.0.92.dist-info/METADATA
pystools-0.0.92.dist-info/WHEEL
pystools-0.0.92.dist-info/top_level.txt
pystools-0.0.92.dist-info/RECORD
