Metadata-Version: 2.2
Name: pystools
Version: 0.0.92
Summary: pystools
Author-email: 木坦坦 <devzhao@126.com>
Project-URL: Homepage, https://github.com/devzhaohan/HMTools
Project-URL: Bug Tracker, https://github.com/devzhaohan/HMTools/issues
Classifier: Programming Language :: Python :: 3
Classifier: License :: OSI Approved :: MIT License
Classifier: Operating System :: OS Independent
Requires-Python: >=3.7
License-File: LICENSE
Requires-Dist: requests-toolbelt
Requires-Dist: loguru
Requires-Dist: pika
Requires-Dist: cos-python-sdk-v5
Requires-Dist: oss2
Requires-Dist: urllib3
Requires-Dist: shortuuid
Requires-Dist: webdriver-manager>=4.0.0
Requires-Dist: selenium>=4.10.0
Requires-Dist: python-dateutil
Requires-Dist: pytz
